tests/__init__.py
tests/run_tests.py
tests/test_analyzer.py
tests/test_cleaner.py
tests/test_finder.py
venvkiller/__init__.py
venvkiller/analyzer.py
venvkiller/cleaner.py
venvkiller/cli.py
venvkiller/finder.py
venvkiller-1.0.0.dist-info/licenses/LICENSE
venvkiller-1.0.0.dist-info/METADATA
venvkiller-1.0.0.dist-info/WHEEL
venvkiller-1.0.0.dist-info/entry_points.txt
venvkiller-1.0.0.dist-info/top_level.txt
venvkiller-1.0.0.dist-info/RECORD
